setup.py
NEUS642_fake_package/__init__.py
NEUS642_fake_package.egg-info/PKG-INFO
NEUS642_fake_package.egg-info/SOURCES.txt
NEUS642_fake_package.egg-info/dependency_links.txt
NEUS642_fake_package.egg-info/top_level.txt