Metadata-Version: 1.0
Name: NEUS642-fake-package
Version: 0.0.4
Summary: Fake package
Home-page: UNKNOWN
Author: Brad Buran
Author-email: buran@ohsu.edu
License: UNKNOWN
Platform: UNKNOWN
